{"eng":{"1":[["Now","H1961"],[" ",null],["when all","H3605"],[" ",null],["the Amorite","H567"],[" ",null],["kings","H4428"],[". . .","H834"],[" ",null],["vvv","H5676"],[" ",null],["west of","H3220"],[" ",null],["the Jordan","H3383"],[" ",null],["and all","H3605"],[" ",null],["the Canaanite","H3669"],[" ",null],["-","H834"],[" ",null],["kings","H4428"],[" ",null],["along","H5921"],[" ",null],["the coast","H3220"],[" ",null],["-","H853"],[" ",null],["heard","H8085"],[" ",null],["how","H834"],[" ",null],["the LORD","H3068"],[" ",null],["-","H853"],[" ",null],["had dried up","H3001"],[" ",null],["the waters","H4325"],[" ",null],["of the Jordan","H3383"],[" ",null],["before","H6440"],[" ",null],["the Israelites","H1121"],[". . .","H3478"],[" ",null],["until","H5704"],[" ",null],["they had crossed over","H5674"],[", ",null],["their hearts","H3824"],[" ",null],["melted","H4549"],[" ",null],["and their spirits","H7307"],[" ",null],["failed","H3808"],[". . .","H1961"],[" ",null],["-","H5750"],[" ",null],["for fear of","H6440"],[" ",null],["the Israelites","H1121"],[". . .","H3478"],[".",null]],"2":[["At that","H1931"],[" ",null],["time","H6256"],[" ",null],["the LORD","H3068"],[" ",null],["said","H559"],[" ",null],["to","H413"],[" ",null],["Joshua","H3091"],[", “",null],["Make","H6213"],[" ",null],["flint","H6697"],[" ",null],["knives","H2719"],[" ",null],["and circumcise","H4135"],[" ",null],["-","H853"],[" ",null],["the sons","H1121"],[" ",null],["of Israel","H3478"],[" ",null],["once again","H7725"],[". . .","H8145"],[".”",null]],"3":[["So Joshua","H3091"],[" ",null],["made","H6213"],[" ",null],["flint","H6697"],[" ",null],["knives","H2719"],[" ",null],["and circumcised","H4135"],[" ",null],["-","H853"],[" ",null],["the sons","H1121"],[" ",null],["of Israel","H3478"],[" ",null],["at","H413"],[" ",null],["Gibeath-haaraloth","H1389"],[". . .","H6190"],[".",null]],"4":[["Now this","H2088"],[" ",null],["is why","H1697"],[" ",null],["-","H834"],[" ",null],["Joshua","H3091"],[" ",null],["circumcised them","H4135"],[": ",null],["All","H3605"],[" ",null],["those","H5971"],[" ",null],["who came out","H3318"],[" ",null],["of Egypt","H4714"],["— ",null],["-","H2145"],[" ",null],["all","H3605"],[" ",null],["the men","H582"],[" ",null],["of war","H4421"],["— ",null],["had died","H4191"],[" ",null],["on the journey","H1870"],[" ",null],["in the wilderness","H4057"],[" ",null],["after they had left","H3318"],[" ",null],["Egypt","H4714"],[".",null]],"5":[["Though","H3588"],[" ",null],["all","H3605"],[". . .","H5971"],[" ",null],["who had come out","H3318"],[" ",null],["were","H1961"],[" ",null],["circumcised","H4135"],[", ",null],["none","H3605"],[". . .","H3808"],[" ",null],["of those","H5971"],[" ",null],["born","H3209"],[" ",null],["in the wilderness","H4057"],[" ",null],["on the journey","H1870"],[" ",null],["vvv","H3318"],[" ",null],["from Egypt","H4714"],[" ",null],["had been circumcised","H4135"],[".",null]],"6":[["For","H3588"],[" ",null],["the Israelites","H1121"],[". . .","H3478"],[" ",null],["had wandered","H1980"],[" ",null],["in the wilderness","H4057"],[" ",null],["forty","H705"],[" ",null],["years","H8141"],[", ",null],["until","H5704"],[" ",null],["all","H3605"],[" ",null],["the nation’s","H1471"],[" ",null],["men","H582"],[" ",null],["of war","H4421"],[" ",null],["who had come out","H3318"],[" ",null],["of Egypt","H4714"],[" ",null],["had died","H8552"],[", ",null],["since","H834"],[" ",null],["they did not","H3808"],[" ",null],["obey","H8085"],[". . .","H6963"],[" ",null],["the LORD","H3068"],[". ",null],["So","H834"],[" ",null],["the LORD","H3068"],[" ",null],["vowed","H7650"],[" ",null],["never","H1115"],[" ",null],["to let them see","H7200"],[" ",null],["-","H853"],[" ",null],["the land","H776"],[" ",null],["-","H834"],[" ",null],["He","H3068"],[" ",null],["had sworn","H7650"],[" ",null],["to their fathers","H1"],[" ",null],["to give","H5414"],[" us, ",null],["a land","H776"],[" ",null],["flowing","H2100"],[" ",null],["with milk","H2461"],[" ",null],["and honey","H1706"],[".",null]],"7":[["And","H853"],[" ",null],["He raised up","H6965"],[" ",null],["their sons","H1121"],[" ",null],["in their place","H8478"],[", ",null],["and these were the ones","H853"],[" ",null],["Joshua","H3091"],[" ",null],["circumcised","H4135"],[". ",null],["[Until this time] they were","H1961"],[". . .","H3588"],[" ",null],["still uncircumcised","H6189"],[", ",null],["since","H3588"],[" ",null],["they had not","H3808"],[" ",null],["been circumcised","H4135"],[" ",null],["-","H853"],[" ",null],["along the way","H1870"],[".",null]],"8":[["And","H1961"],[" ",null],["after","H834"],[". . .","H8552"],[" ",null],["all","H3605"],[" ",null],["the nation","H1471"],[" ",null],["had been circumcised","H4135"],[", ",null],["they stayed","H3427"],[" ",null],["there","H8478"],[" ",null],["in the camp","H4264"],[" ",null],["until","H5704"],[" ",null],["they were healed","H2421"],[".",null]],"9":[["Then the LORD","H3068"],[" ",null],["said","H559"],[" ",null],["to","H413"],[" ",null],["Joshua","H3091"],[", “",null],["Today","H3117"],[" ",null],["I have rolled away","H1556"],[" ",null],["-","H853"],[" ",null],["the reproach","H2781"],[" ",null],["of Egypt","H4714"],[" ",null],["from you","H5921"],[".” ",null],["So that","H1931"],[" ",null],["place","H4725"],[" ",null],["has been called","H7121"],[". . .","H8034"],[" ",null],["Gilgal","H1537"],[" ",null],["to","H5704"],[" ",null],["this","H2088"],[" ",null],["day","H3117"],[".",null]],"10":[["On the evening","H6153"],[" ",null],["of the fourteenth","H702"],[". . .","H6240"],[" ",null],["day","H3117"],[" ",null],["of the month","H2320"],[", ",null],["while the Israelites","H1121"],[". . .","H3478"],[" ",null],["were camped","H2583"],[" ",null],["at Gilgal","H1537"],[" ",null],["on the plains","H6160"],[" ",null],["of Jericho","H3405"],[", ",null],["they kept","H6213"],[" ",null],["-","H853"],[" ",null],["the Passover","H6453"],[".",null]],"11":[["The day after","H4283"],[" ",null],["the Passover","H6453"],[", ",null],["on that very","H6106"],[" ",null],["day","H3117"],[", ",null],[". . .","H2088"],[" ",null],["they ate","H398"],[" ",null],["unleavened bread","H4682"],[" ",null],["and roasted grain","H7033"],[" ",null],["from the produce","H5669"],[" ",null],["of the land","H776"],[".",null]],"12":[["And the day","H4283"],[" ",null],["after they had eaten","H398"],[" ",null],["from the produce","H5669"],[" ",null],["of the land","H776"],[", ",null],["the manna","H4478"],[" ",null],["ceased","H7673"],[". ",null],["There was","H1961"],[" ",null],["no","H3808"],[" ",null],["more","H5750"],[" ",null],["manna","H4478"],[" ",null],["for the Israelites","H1121"],[". . .","H3478"],[", ",null],["so that","H1931"],[" ",null],["year","H8141"],[" ",null],["they began to eat","H398"],[" ",null],["the crops","H8393"],[" ",null],["of the land","H776"],[" ",null],["of Canaan","H3667"],[".",null]],"13":[["Now when Joshua","H3091"],[" ",null],["was","H1961"],[". . .","H1961"],[" ",null],["near Jericho","H3405"],[", ",null],["he looked up","H5375"],[". . .","H5869"],[" ",null],["and saw","H7200"],[". . .","H2009"],[" ",null],["a man","H376"],[" ",null],["standing","H5975"],[" ",null],["in front of him","H5048"],[" ",null],["with a drawn","H8025"],[" ",null],["sword","H2719"],[" ",null],["in His hand","H3027"],[". ",null],["Joshua","H3091"],[" ",null],["approached","H1980"],[" ",null],["Him","H413"],[" ",null],["and asked","H559"],[", “",null],["Are You","H859"],[" for us ",null],["or","H518"],[" ",null],["for our enemies","H6862"],["?”",null]],"14":[["“",null],["Neither","H3808"],[",” ",null],[". . .","H3588"],[" ",null],["He replied","H559"],[". “",null],["I","H589"],[" ",null],["have now","H6258"],[" ",null],["come","H935"],[" ",null],["as Commander","H8269"],[" ",null],["of the LORD’s","H3068"],[" ",null],["army","H6635"],[".” ",null],["Then Joshua","H3091"],[" ",null],["fell","H5307"],[" ",null],["facedown","H413"],[". . .","H6440"],[". . .","H776"],[" ",null],["in reverence","H7812"],[" ",null],["and asked","H559"],[" Him, “",null],["What","H4100"],[" ",null],["does my Lord","H113"],[" ",null],["have to say","H1696"],[" ",null],["to","H413"],[" ",null],["His servant","H5650"],["?”",null]],"15":[["The Commander","H8269"],[" ",null],["of the LORD’s","H3068"],[" ",null],["army","H6635"],[" ",null],["replied","H559"],[" ",null],["-","H413"],[" ",null],["-","H3091"],[", “",null],["Take off","H5394"],[" ",null],["your sandals","H5275"],[" ",null],["-","H5921"],[" ",null],["-","H7272"],[", ",null],["for","H3588"],[" ",null],["the place","H4725"],[" ",null],["where","H834"],[" ",null],["you","H859"],[" ",null],["are standing","H5975"],[". . .","H5921"],[" ",null],["is holy","H6944"],[". . .","H1931"],[".” ",null],["And Joshua","H3091"],[" ",null],["did","H6213"],[" ",null],["so","H3651"],[".",null]]},"heb":{"1":[["וַיְהִ֣י","H1961"],["כִשְׁמֹ֣עַ","H8085"],["כָּל־","H3605"],["מַלְכֵ֣י","H4428"],["הָאֱמֹרִ֡י","H567"],["אֲשֶׁר֩","H834"],["בְּעֵ֨בֶר","H5676"],["הַיַּרְדֵּ֜ן","H3383"],["יָ֗מָּה","H3220"],["וְכָל־","H3605"],["מַלְכֵ֤י","H4428"],["הַֽכְּנַעֲנִי֙","H3669"],["אֲשֶׁ֣ר","H834"],["עַל־","H5921"],["הַיָּ֔ם","H3220"],["אֵ֠ת","H853"],["אֲשֶׁר־","H834"],["הוֹבִ֨ישׁ","H3001"],["יְהוָ֜ה","H3068"],["אֶת־","H853"],["מֵ֧י","H4325"],["הַיַּרְדֵּ֛ן","H3383"],["מִפְּנֵ֥י","H6440"],["בְנֵֽי־","H1121"],["יִשְׂרָאֵ֖ל","H3478"],["עַד־","H5704"],["עָבְרָנוּ","H5674"],["וַיִּמַּ֣ס","H4549"],["לְבָבָ֗ם","H3824"],["וְלֹא־","H3808"],["הָ֨יָה","H1961"],["בָ֥ם",null],["עוֹד֙","H5750"],["ר֔וּחַ","H7307"],["מִפְּנֵ֖י","H6440"],["בְּנֵֽי־","H1121"],["יִשְׂרָאֵֽל׃ס","H3478"]],"2":[["בָּעֵ֣ת","H6256"],["הַהִ֗יא","H1931"],["אָמַ֤ר","H559"],["יְהוָה֙","H3068"],["אֶל־","H413"],["יְהוֹשֻׁ֔עַ","H3091"],["עֲשֵׂ֥ה","H6213"],["לְךָ֖",null],["חַֽרְב֣וֹת","H2719"],["צֻרִ֑ים","H6697"],["וְשׁ֛וּב","H7725"],["מֹ֥ל","H4135"],["אֶת־","H853"],["בְּנֵֽי־","H1121"],["יִשְׂרָאֵ֖ל","H3478"],["שֵׁנִֽית׃","H8145"]],"3":[["וַיַּעַשׂ־","H6213"],["ל֥וֹ",null],["יְהוֹשֻׁ֖עַ","H3091"],["חַֽרְב֣וֹת","H2719"],["צֻרִ֑ים","H6697"],["וַיָּ֙מָל֙","H4135"],["אֶת־","H853"],["בְּנֵ֣י","H1121"],["יִשְׂרָאֵ֔ל","H3478"],["אֶל־","H413"],["גִּבְעַ֖ת","H1389"],["הָעֲרָלֽוֹת׃","H6190"]],"4":[["וְזֶ֥ה","H2088"],["הַדָּבָ֖ר","H1697"],["אֲשֶׁר־","H834"],["מָ֣ל","H4135"],["יְהוֹשֻׁ֑עַ","H3091"],["כָּל־","H3605"],["הָעָ֣ם","H5971"],["הַיֹּצֵא֩","H3318"],["מִמִּצְרַ֨יִם","H4714"],["הַזְּכָרִ֜ים","H2145"],["כֹּ֣ל׀","H3605"],["אַנְשֵׁ֣י","H582"],["הַמִּלְחָמָ֗ה","H4421"],["מֵ֤תוּ","H4191"],["בַמִּדְבָּר֙","H4057"],["בַּדֶּ֔רֶךְ","H1870"],["בְּצֵאתָ֖ם","H3318"],["מִמִּצְרָֽיִם׃","H4714"]],"5":[["כִּֽי־","H3588"],["מֻלִ֣ים","H4135"],["הָי֔וּ","H1961"],["כָּל־","H3605"],["הָעָ֖ם","H5971"],["הַיֹּֽצְאִ֑ים","H3318"],["וְכָל־","H3605"],["הָ֠עָם","H5971"],["הַיִּלֹּדִ֨ים","H3209"],["בַּמִּדְבָּ֥ר","H4057"],["בַּדֶּ֛רֶךְ","H1870"],["בְּצֵאתָ֥ם","H3318"],["מִמִּצְרַ֖יִם","H4714"],["לֹא־","H3808"],["מָֽלוּ׃","H4135"]],"6":[["כִּ֣י׀","H3588"],["אַרְבָּעִ֣ים","H705"],["שָׁנָ֗ה","H8141"],["הָלְכ֣וּ","H1980"],["בְנֵֽי־","H1121"],["יִשְׂרָאֵל֮","H3478"],["בַּמִּדְבָּר֒","H4057"],["עַד־","H5704"],["תֹּ֨ם","H8552"],["כָּל־","H3605"],["הַגּ֜וֹי","H1471"],["אַנְשֵׁ֤י","H582"],["הַמִּלְחָמָה֙","H4421"],["הַיֹּצְאִ֣ים","H3318"],["מִמִּצְרַ֔יִם","H4714"],["אֲשֶׁ֥ר","H834"],["לֹֽא־","H3808"],["שָׁמְע֖וּ","H8085"],["בְּק֣וֹל","H6963"],["יְהוָ֑ה","H3068"],["אֲשֶׁ֨ר","H834"],["נִשְׁבַּ֤ע","H7650"],["יְהוָה֙","H3068"],["לָהֶ֔ם",null],["לְבִלְתִּ֞י","H1115"],["הַרְאוֹתָ֣ם","H7200"],["אֶת־","H853"],["הָאָ֗רֶץ","H776"],["אֲשֶׁר֩","H834"],["נִשְׁבַּ֨ע","H7650"],["יְהוָ֤ה","H3068"],["לַֽאֲבוֹתָם֙","H1"],["לָ֣תֶת","H5414"],["לָ֔נוּ",null],["אֶ֛רֶץ","H776"],["זָבַ֥ת","H2100"],["חָלָ֖ב","H2461"],["וּדְבָֽשׁ׃","H1706"]],"7":[["וְאֶת־","H853"],["בְּנֵיהֶם֙","H1121"],["הֵקִ֣ים","H6965"],["תַּחְתָּ֔ם","H8478"],["אֹתָ֖ם","H853"],["מָ֣ל","H4135"],["יְהוֹשֻׁ֑עַ","H3091"],["כִּי־","H3588"],["עֲרֵלִ֣ים","H6189"],["הָי֔וּ","H1961"],["כִּ֛י","H3588"],["לֹא־","H3808"],["מָ֥לוּ","H4135"],["אוֹתָ֖ם","H853"],["בַּדָּֽרֶךְ׃","H1870"]],"8":[["וַיְהִ֛י","H1961"],["כַּאֲשֶׁר־","H834"],["תַּ֥מּוּ","H8552"],["כָל־","H3605"],["הַגּ֖וֹי","H1471"],["לְהִמּ֑וֹל","H4135"],["וַיֵּשְׁב֥וּ","H3427"],["תַחְתָּ֛ם","H8478"],["בַּֽמַּחֲנֶ֖ה","H4264"],["עַ֥ד","H5704"],["חֲיוֹתָֽם׃פ","H2421"]],"9":[["וַיֹּ֤אמֶר","H559"],["יְהוָה֙","H3068"],["אֶל־","H413"],["יְהוֹשֻׁ֔עַ","H3091"],["הַיּ֗וֹם","H3117"],["גַּלּ֛וֹתִי","H1556"],["אֶת־","H853"],["חֶרְפַּ֥ת","H2781"],["מִצְרַ֖יִם","H4714"],["מֵעֲלֵיכֶ֑ם","H5921"],["וַיִּקְרָ֞א","H7121"],["שֵׁ֣ם","H8034"],["הַמָּק֤וֹם","H4725"],["הַהוּא֙","H1931"],["גִּלְגָּ֔ל","H1537"],["עַ֖ד","H5704"],["הַיּ֥וֹם","H3117"],["הַזֶּֽה׃","H2088"]],"10":[["וַיַּחֲנ֥וּ","H2583"],["בְנֵֽי־","H1121"],["יִשְׂרָאֵ֖ל","H3478"],["בַּגִּלְגָּ֑ל","H1537"],["וַיַּעֲשׂ֣וּ","H6213"],["אֶת־","H853"],["הַפֶּ֡סַח","H6453"],["בְּאַרְבָּעָה֩","H702"],["עָשָׂ֨ר","H6240"],["י֥וֹם","H3117"],["לַחֹ֛דֶשׁ","H2320"],["בָּעֶ֖רֶב","H6153"],["בְּעַֽרְב֥וֹת","H6160"],["יְרִיחֽוֹ׃","H3405"]],"11":[["וַיֹּ֨אכְל֜וּ","H398"],["מֵעֲב֥וּר","H5669"],["הָאָ֛רֶץ","H776"],["מִמָּֽחֳרַ֥ת","H4283"],["הַפֶּ֖סַח","H6453"],["מַצּ֣וֹת","H4682"],["וְקָל֑וּי","H7033"],["בְּעֶ֖צֶם","H6106"],["הַיּ֥וֹם","H3117"],["הַזֶּֽה׃","H2088"]],"12":[["וַיִּשְׁבֹּ֨ת","H7673"],["הַמָּ֜ן","H4478"],["מִֽמָּחֳרָ֗ת","H4283"],["בְּאָכְלָם֙","H398"],["מֵעֲב֣וּר","H5669"],["הָאָ֔רֶץ","H776"],["וְלֹא־","H3808"],["הָ֥יָה","H1961"],["ע֛וֹד","H5750"],["לִבְנֵ֥י","H1121"],["יִשְׂרָאֵ֖ל","H3478"],["מָ֑ן","H4478"],["וַיֹּאכְל֗וּ","H398"],["מִתְּבוּאַת֙","H8393"],["אֶ֣רֶץ","H776"],["כְּנַ֔עַן","H3667"],["בַּשָּׁנָ֖ה","H8141"],["הַהִֽיא׃ס","H1931"]],"13":[["וַיְהִ֗י","H1961"],["בִּֽהְי֣וֹת","H1961"],["יְהוֹשֻׁעַ֮","H3091"],["בִּירִיחוֹ֒","H3405"],["וַיִּשָּׂ֤א","H5375"],["עֵינָיו֙","H5869"],["וַיַּ֔רְא","H7200"],["וְהִנֵּה־","H2009"],["אִישׁ֙","H376"],["עֹמֵ֣ד","H5975"],["לְנֶגְדּ֔וֹ","H5048"],["וְחַרְבּ֥וֹ","H2719"],["שְׁלוּפָ֖ה","H8025"],["בְּיָד֑וֹ","H3027"],["וַיֵּ֨לֶךְ","H1980"],["יְהוֹשֻׁ֤עַ","H3091"],["אֵלָיו֙","H413"],["וַיֹּ֣אמֶר","H559"],["ל֔וֹ",null],["הֲלָ֥נוּ",null],["אַתָּ֖ה","H859"],["אִם־","H518"],["לְצָרֵֽינוּ׃","H6862"]],"14":[["וַיֹּ֣אמֶר׀","H559"],["לֹ֗א","H3808"],["כִּ֛י","H3588"],["אֲנִ֥י","H589"],["שַׂר־","H8269"],["צְבָֽא־","H6635"],["יְהוָ֖ה","H3068"],["עַתָּ֣ה","H6258"],["בָ֑אתִי","H935"],["וַיִּפֹּל֩","H5307"],["יְהוֹשֻׁ֨עַ","H3091"],["אֶל־","H413"],["פָּנָ֥יו","H6440"],["אַ֙רְצָה֙","H776"],["וַיִּשְׁתָּ֔חוּ","H7812"],["וַיֹּ֣אמֶר","H559"],["ל֔וֹ",null],["מָ֥ה","H4100"],["אֲדֹנִ֖י","H113"],["מְדַבֵּ֥ר","H1696"],["אֶל־","H413"],["עַבְדּֽוֹ׃","H5650"]],"15":[["וַיֹּאמֶר֩","H559"],["שַׂר־","H8269"],["צְבָ֨א","H6635"],["יְהוָ֜ה","H3068"],["אֶל־","H413"],["יְהוֹשֻׁ֗עַ","H3091"],["שַׁל־","H5394"],["נַֽעַלְךָ֙","H5275"],["מֵעַ֣ל","H5921"],["רַגְלֶ֔ךָ","H7272"],["כִּ֣י","H3588"],["הַמָּק֗וֹם","H4725"],["אֲשֶׁ֥ר","H834"],["אַתָּ֛ה","H859"],["עֹמֵ֥ד","H5975"],["עָלָ֖יו","H5921"],["קֹ֣דֶשׁ","H6944"],["ה֑וּא","H1931"],["וַיַּ֥עַשׂ","H6213"],["יְהוֹשֻׁ֖עַ","H3091"],["כֵּֽן׃","H3651"]]}}