{"eng":{"1":[["I hope","G3785"],[" ",null],["you will put up with","G430"],[" ",null],["a","G5100"],[" ",null],["little","G3398"],[" ",null],["of my","G1473"],[" ",null],["foolishness","G877"],[", ",null],["but","G235"],[". . .","G2532"],[" ",null],["[you are already doing that]","G430"],[". . .","G1473"],[".",null]],"2":[["-","G1063"],[" ",null],["I am jealous for","G2206"],[" ",null],["you","G4771"],[" ",null],["with a godly","G2316"],[" ",null],["jealousy","G2205"],[". ",null],["For","G1063"],[" ",null],["I promised","G718"],[" ",null],["you","G4771"],[" ",null],["to one","G1520"],[" ",null],["husband","G435"],[", ",null],["to present [you]","G3936"],[" ",null],["[as] a pure","G53"],[" ",null],["virgin","G3933"],[" ",null],["-","G3588"],[" ",null],["to Christ","G5547"],[".",null]],"3":[["I am afraid","G5399"],[" ",null],["-","G3361"],[", ",null],["however","G1161"],[", ",null],["that just","G4459"],[" ",null],["as","G5613"],[" ",null],["Eve","G2096"],[" ",null],["was deceived","G1818"],[" ",null],["by","G1722"],[" ",null],["the","G3588"],[" ",null],["serpent’s","G3789"],[" ",null],["-","G846"],[" ",null],["-","G3588"],[" ",null],["cunning","G3834"],[", ",null],["your","G4771"],[" ",null],["-","G3588"],[" ",null],["minds","G3540"],[" ",null],["may be led astray","G5351"],[" ",null],["from","G575"],[" ",null],["[your]","G3588"],[" ",null],["simple","G572"],[" ",null],["and","G2532"],[" ",null],["-","G3588"],[" ",null],["pure [devotion]","G54"],[" ",null],["-","G3588"],[" ",null],["to","G1519"],[" ",null],["-","G3588"],[" ",null],["Christ","G5547"],[".",null]],"4":[["For","G1063"],[" ",null],["if","G1487"],[" ",null],["-","G3303"],[" ",null],["[someone]","G3588"],[" ",null],["comes","G2064"],[" ",null],["[and] proclaims","G2784"],[" ",null],["[a] Jesus","G2424"],[" ",null],["other","G243"],[" ",null],["[than the One]","G3739"],[". . .","G3756"],[" ",null],["we proclaimed","G2784"],[", ",null],["or if","G2228"],[" ",null],["you receive","G2983"],[" ",null],["a different","G2087"],[" ",null],["spirit","G4151"],[" ",null],["[than the One]","G3739"],[". . .","G3756"],[" ",null],["you received","G2983"],[", ",null],["or","G2228"],[" ",null],["a different","G2087"],[" ",null],["gospel","G2098"],[" ",null],["[than the one]","G3739"],[". . .","G3756"],[" ",null],["you accepted","G1209"],[", ",null],["you put up with it","G430"],[" ",null],["very easily","G2573"],[".",null]],"5":[["-","G1063"],[" ",null],["I consider myself","G3049"],[" ",null],["in no way","G3367"],[" ",null],["inferior","G5302"],[" ",null],["to those","G3588"],[" “",null],["super-apostles","G5228"],[". . .","G652"],[".”",null]],"6":[["-","G1161"],[" ",null],["Although","G2532"],[". . .","G1487"],[" ",null],["[I am] not a polished","G2399"],[" ",null],["-","G3588"],[" ",null],["speaker","G3056"],[", ",null],["vvv","G235"],[" ",null],["I am certainly not lacking","G3756"],[" ",null],["-","G3588"],[" ",null],["in knowledge","G1108"],[". ",null],["-","G235"],[" ",null],["We have made this clear","G5319"],[" ",null],["to","G1519"],[" ",null],["you","G4771"],[" ",null],["in","G1722"],[" ",null],["every way possible","G3956"],[". . .","G1722"],[". . .","G3956"],[".",null]],"7":[["[Was it]","G2228"],[" ",null],["a sin","G266"],[" ",null],["[for me]","G4160"],[" ",null],["to humble","G5013"],[" ",null],["myself","G1683"],[" ",null],["in order to","G2443"],[" ",null],["vvv","G4771"],[" ",null],["exalt you","G5312"],[", ",null],["because","G3754"],[" ",null],["I preached","G2097"],[" ",null],["the","G3588"],[" ",null],["gospel","G2098"],[" ",null],["-","G3588"],[" ",null],["of God","G2316"],[" ",null],["to you","G4771"],[" ",null],["free of charge","G1432"],["?",null]],"8":[["I robbed","G4813"],[" ",null],["other","G243"],[" ",null],["churches","G1577"],[" ",null],["by accepting","G2983"],[" ",null],["[their] support","G3800"],[" ",null],["in order","G4314"],[" ",null],["-","G3588"],[" ",null],["to serve","G1248"],[" ",null],["you","G4771"],[".",null]],"9":[["And","G2532"],[" ",null],["when I was","G3918"],[" ",null],["with","G4314"],[" ",null],["you","G4771"],[" ",null],["and","G2532"],[" ",null],["in need","G5302"],[", ",null],["vvv","G3756"],[" ",null],["I was not a burden","G2655"],[" ",null],["[to anyone]","G3762"],["; ",null],["for","G1063"],[" ",null],["the","G3588"],[" ",null],["brothers","G80"],[" ",null],["who came","G2064"],[" ",null],["from","G575"],[" ",null],["Macedonia","G3109"],[" ",null],["supplied","G4322"],[" ",null],["my","G1473"],[" ",null],["-","G3588"],[" ",null],["needs","G5303"],[". ",null],["-","G2532"],[" ",null],["I have refrained","G5083"],[". . .","G1683"],[" ",null],["from being a burden","G4"],[" ",null],["to you","G4771"],[" ",null],["in","G1722"],[" ",null],["any way","G3956"],[", ",null],["and","G2532"],[" ",null],["I will continue to do so","G5083"],[".",null]],"10":[["[As surely as the] truth","G225"],[" ",null],["of Christ","G5547"],[" ",null],["is","G1510"],[" ",null],["in","G1722"],[" ",null],["me","G1473"],[", ",null],["-","G3754"],[" ",null],["this","G3778"],[" ",null],["-","G3588"],[" ",null],["boasting","G2746"],[" ",null],["of","G1519"],[" ",null],["mine","G1473"],[" ",null],["vvv","G3756"],[" ",null],["will not be silenced","G5420"],[" ",null],["in","G1722"],[" ",null],["the","G3588"],[" ",null],["regions","G2824"],[" ",null],["-","G3588"],[" ",null],["of Achaia","G882"],[".",null]],"11":[["Why","G1223"],[". . .","G5101"],["? ",null],["Because","G3754"],[" ",null],["vvv","G3756"],[" ",null],["I do not love","G25"],[" ",null],["you","G4771"],["? ",null],["-","G3588"],[" ",null],["God","G2316"],[" ",null],["knows [I do]","G1492"],["!",null]],"12":[["But","G1161"],[" ",null],["vvv","G2532"],[" ",null],["I will keep on doing","G4160"],[" ",null],["what","G3739"],[" ",null],["I am doing","G4160"],[", ",null],["in order","G2443"],[" ",null],["to undercut","G1581"],[" ",null],["-","G3588"],[" ",null],["-","G874"],[" ",null],["those who","G3588"],[" ",null],["want","G2309"],[" ",null],["an opportunity","G874"],[" ",null],["to","G2443"],[" ",null],["be regarded as","G2147"],[" ",null],["our equals","G2531"],[". . .","G2532"],[". . .","G1473"],[" ",null],["in","G1722"],[" ",null],["the things","G3739"],[" ",null],["of which they boast","G2744"],[".",null]],"13":[["For","G1063"],[" ",null],["-","G3588"],[" ",null],["such men [are]","G5108"],[" ",null],["false apostles","G5570"],[", ",null],["deceitful","G1386"],[" ",null],["workers","G2040"],[", ",null],["masquerading","G3345"],[" ",null],["as","G1519"],[" ",null],["apostles","G652"],[" ",null],["of Christ","G5547"],[".",null]],"14":[["And","G2532"],[" ",null],["no","G3756"],[" ",null],["wonder","G2295"],[", ",null],["for","G1063"],[" ",null],["-","G3588"],[" ",null],["Satan","G4567"],[" ",null],["himself","G846"],[" ",null],["masquerades","G3345"],[" ",null],["as","G1519"],[" ",null],["an angel","G32"],[" ",null],["of light","G5457"],[".",null]],"15":[["[It is] not","G3756"],[" ",null],["surprising","G3173"],[", ",null],["then","G3767"],[", ",null],["if","G1487"],[" ",null],["his","G846"],[" ",null],["-","G3588"],[" ",null],["servants","G1249"],[" ",null],["-","G2532"],[" ",null],["masquerade","G3345"],[" ",null],["as","G5613"],[" ",null],["servants","G1249"],[" ",null],["of righteousness","G1343"],[". ",null],["[Their]","G3739"],[" ",null],["-","G3588"],[" ",null],["end","G5056"],[" ",null],["will correspond to","G1510"],[". . .","G2596"],[" ",null],["their","G846"],[" ",null],["-","G3588"],[" ",null],["actions","G2041"],[".",null]],"16":[["vvv","G3825"],[" ",null],["I repeat","G3004"],[": ",null],["{Let} no","G3361"],[" ",null],["one","G5100"],[" ",null],["take","G1380"],[" ",null],["me","G1473"],[" ",null],["for","G1510"],[" ",null],["a fool","G878"],[". ",null],["But","G1161"],[" ",null],["if","G1487"],[" ",null],["[you do]","G1490"],[", ",null],["[then] receive","G1209"],[" ",null],["me","G1473"],[" ",null],["-","G2579"],[" ",null],["as","G5613"],[" ",null],["a fool","G878"],[", ",null],["so that","G2443"],[" ",null],["I too","G2504"],[" ",null],["may boast","G2744"],[" ",null],["a","G5100"],[" ",null],["little","G3398"],[".",null]],"17":[["-","G3739"],[" ",null],["-","G2980"],[" ",null],["In","G1722"],[" ",null],["this","G3778"],[" ",null],["-","G3588"],[" ",null],["confident","G5287"],[" ",null],["-","G3588"],[" ",null],["boasting [of mine]","G2746"],[", ",null],["vvv","G3756"],[" ",null],["I am not speaking","G2980"],[" ",null],["as","G2596"],[" ",null],["[the] Lord {would}","G2962"],[", ",null],["but","G235"],[" ",null],["as","G5613"],[" ",null],["-","G1722"],[" ",null],["a fool","G877"],[".",null]],"18":[["Since","G1893"],[" ",null],["many","G4183"],[" ",null],["are boasting","G2744"],[" ",null],["according to","G2596"],[" ",null],["the","G3588"],[" ",null],["flesh","G4561"],[", ",null],["I too","G2504"],[" ",null],["will boast","G2744"],[".",null]],"19":[["For","G1063"],[" ",null],["you gladly put up with","G430"],[". . .","G2234"],[" ",null],["-","G3588"],[" ",null],["fools","G878"],[", ",null],["since you are","G1510"],[" ",null],["so wise","G5429"],[".",null]],"20":[["In fact","G1063"],[", ",null],["you even put up with","G430"],[" ",null],["-","G1487"],[" ",null],["anyone who","G5100"],[" ",null],["enslaves","G2615"],[" ",null],["you","G4771"],[" ",null],["[or]","G1487"],[". . .","G5100"],[" ",null],["exploits [you]","G2719"],[" ",null],["[or]","G1487"],[". . .","G5100"],[" ",null],["takes advantage [of you]","G2983"],[" ",null],["[or]","G1487"],[". . .","G5100"],[" ",null],["exalts himself","G1869"],[" ",null],["[or]","G1487"],[". . .","G5100"],[" ",null],["strikes","G1194"],[" ",null],["you","G4771"],[" ",null],["in","G1519"],[" ",null],["the face","G4383"],[".",null]],"21":[["To","G2596"],[" ",null],["[my] shame","G819"],[" ",null],["I concede","G3004"],[" ",null],["-","G5613"],[" ",null],["that","G3754"],[" ",null],["we","G1473"],[" ",null],["were too weak [for that]","G770"],["! ",null],["Speaking","G3004"],[" ",null],["vvv","G1722"],[" ",null],["as a fool","G877"],[", ",null],["however","G1161"],[", ",null],["I can","G2504"],[" ",null],["[match]","G5111"],[" ",null],["-","G1722"],[" ",null],["what","G3739"],[" ",null],["anyone else","G5100"],[". . .","G302"],[" ",null],["dares [to boast about]","G5111"],[".",null]],"22":[["Are they","G1510"],[" ",null],["Hebrews","G1445"],["? ",null],["So am I","G2504"],[". ",null],["Are they","G1510"],[" ",null],["Israelites","G2475"],["? ",null],["So am I","G2504"],[". ",null],["Are they","G1510"],[" ",null],["descendants","G4690"],[" ",null],["of Abraham","G11"],["? ",null],["So am I","G2504"],[".",null]],"23":[["Are they","G1510"],[" ",null],["servants","G1249"],[" ",null],["of Christ","G5547"],["? (",null],["I am speaking","G2980"],[" ",null],["as if I were out of my mind","G3912"],[".) ",null],["I am","G1473"],[" ",null],["so much more","G5228"],[": ",null],["in","G1722"],[" ",null],["harder","G4057"],[" ",null],["labor","G2873"],[", ",null],["in","G1722"],[" ",null],["more","G4057"],[" ",null],["imprisonments","G5438"],[", ",null],["in","G1722"],[" ",null],["worse","G5234"],[" ",null],["beatings","G4127"],[", ",null],["in","G1722"],[" ",null],["frequent","G4178"],[" ",null],["danger of death","G2288"],[".",null]],"24":[["Five times","G3999"],[" ",null],["I received","G2983"],[" ",null],["from","G5259"],[" ",null],["[the] Jews","G2453"],[" ",null],["[the] forty [lashes]","G5062"],[" ",null],["minus","G3844"],[" ",null],["one","G1520"],[".",null]],"25":[["Three times","G5151"],[" ",null],["I was beaten with rods","G4463"],[", ",null],["once","G530"],[" ",null],["I was stoned","G3034"],[", ",null],["three times","G5151"],[" ",null],["I was shipwrecked","G3489"],[". ",null],["I spent","G4160"],[" ",null],["a night and a day","G3574"],[" ",null],["in","G1722"],[" ",null],["the","G3588"],[" ",null],["open [sea]","G1037"],[".",null]],"26":[["In my frequent journeys","G3597"],[". . .","G4178"],[", ",null],["[I have been] in danger","G2794"],[" ",null],["from rivers","G4215"],[" ",null],["[and]","G2794"],[" ",null],["from bandits","G3027"],[", ",null],["in danger","G2794"],[" ",null],["from [my]","G1537"],[" ",null],["countrymen","G1085"],[" ",null],["[and]","G2794"],[" ",null],["from","G1537"],[" ",null],["[the] Gentiles","G1484"],[", ",null],["in danger","G2794"],[" ",null],["in","G1722"],[" ",null],["[the] city","G4172"],[" ",null],["[and]","G2794"],[" ",null],["in","G1722"],[" ",null],["[the] country","G2047"],[", ",null],["in danger","G2794"],[" ",null],["on","G1722"],[" ",null],["[the] sea","G2281"],[" ",null],["[and]","G2794"],[" ",null],["among","G1722"],[" ",null],["false brothers","G5569"],[",",null]],"27":[["in labor","G2873"],[" ",null],["and","G2532"],[" ",null],["toil","G3449"],[" ",null],["[and] often","G4178"],[" ",null],["vvv","G1722"],[" ",null],["without sleep","G70"],[", ",null],["in","G1722"],[" ",null],["hunger","G3042"],[" ",null],["and","G2532"],[" ",null],["thirst","G1373"],[" ",null],["[and] often","G4178"],[" ",null],["vvv","G1722"],[" ",null],["without food","G3521"],[", ",null],["in","G1722"],[" ",null],["cold","G5592"],[" ",null],["and","G2532"],[" ",null],["exposure","G1132"],[".",null]],"28":[["Apart from","G5565"],[" ",null],["these external","G3924"],[" ",null],["[trials]","G3588"],[", ",null],["I [face]","G1473"],[" ",null],["vvv","G2596"],[" ",null],["vvv","G3588"],[" ",null],["daily","G2250"],[" ",null],["the","G3588"],[" ",null],["pressure","G1999"],[" ",null],["[of my]","G3588"],[" ",null],["concern","G3308"],[" ",null],["for all","G3956"],[" ",null],["the","G3588"],[" ",null],["churches","G1577"],[".",null]],"29":[["Who","G5101"],[" ",null],["is weak","G770"],[", ",null],["and","G2532"],[" ",null],["vvv","G3756"],[" ",null],["I am not weak","G770"],["? ",null],["Who","G5101"],[" ",null],["is led into sin","G4624"],[", ",null],["and","G2532"],[" ",null],["I","G1473"],[" ",null],["{do} not","G3756"],[" ",null],["burn with grief","G4448"],["?",null]],"30":[["If","G1487"],[" ",null],["I must","G1163"],[" ",null],["boast","G2744"],[", ",null],["I will boast","G2744"],[" ",null],["[of] the things","G3588"],[" ",null],["[that show]","G3588"],[" ",null],["my","G1473"],[" ",null],["weakness","G769"],[".",null]],"31":[["The","G3588"],[" ",null],["God","G2316"],[" ",null],["and","G2532"],[" ",null],["Father","G3962"],[" ",null],["of the","G3588"],[" ",null],["Lord","G2962"],[" ",null],["Jesus","G2424"],[", ",null],["who","G3588"],[" ",null],["is","G1510"],[" ",null],["vvv","G1519"],[" ",null],["vvv","G3588"],[" ",null],["forever","G165"],[" ",null],["worthy of praise","G2128"],[", ",null],["knows","G1492"],[" ",null],["that","G3754"],[" ",null],["vvv","G3756"],[" ",null],["I am not lying","G5574"],[".",null]],"32":[["In","G1722"],[" ",null],["Damascus","G1154"],[", ",null],["the","G3588"],[" ",null],["governor","G1481"],[" ",null],["under","G3588"],[" ",null],["King","G935"],[" ",null],["Aretas","G702"],[" ",null],["secured","G5432"],[" ",null],["the","G3588"],[" ",null],["city","G4172"],[" ",null],["of the Damascenes","G1153"],[" ",null],["in order to arrest","G4084"],[" ",null],["me","G1473"],[".",null]],"33":[["But","G2532"],[" ",null],["I was lowered","G5465"],[" ",null],["in","G1722"],[" ",null],["a basket","G4553"],[" ",null],["through","G1223"],[" ",null],["a window","G2376"],[" ",null],["in","G1223"],[" ",null],["the","G3588"],[" ",null],["wall","G5038"],[" ",null],["and","G2532"],[" ",null],["escaped","G1628"],[" ",null],["his","G846"],[" ",null],["-","G3588"],[" ",null],["grasp","G5495"],[".",null]]},"grk":{"1":[["Ὄφελον","G3785"],["ἀνείχεσθέ","G430"],["μου","G1473"],["μικρόν","G3398"],["τι","G5100"],["ἀφροσύνης","G877"],["ἀλλὰ","G235"],["καὶ","G2532"],["ἀνέχεσθέ","G430"],["μου","G1473"]],"2":[["ζηλῶ","G2206"],["γὰρ","G1063"],["ὑμᾶς","G4771"],["Θεοῦ","G2316"],["ζήλῳ","G2205"],["ἡρμοσάμην","G718"],["γὰρ","G1063"],["ὑμᾶς","G4771"],["ἑνὶ","G1520"],["ἀνδρὶ","G435"],["παρθένον","G3933"],["ἁγνὴν","G53"],["παραστῆσαι","G3936"],["τῷ","G3588"],["Χριστῷ","G5547"]],"3":[["Φοβοῦμαι","G5399"],["δὲ","G1161"],["μή","G3361"],["πως","G4459"],["ὡς","G5613"],["ὁ","G3588"],["ὄφις","G3789"],["ἐξηπάτησεν","G1818"],["Εὕαν","G2096"],["ἐν","G1722"],["τῇ","G3588"],["πανουργίᾳ","G3834"],["αὐτοῦ","G846"],["φθαρῇ","G5351"],["τὰ","G3588"],["νοήματα","G3540"],["ὑμῶν","G4771"],["ἀπὸ","G575"],["τῆς","G3588"],["ἁπλότητος","G572"],["καὶ","G2532"],["τῆς","G3588"],["ἁγνότητος","G54"],["τῆς","G3588"],["εἰς","G1519"],["τὸν","G3588"],["Χριστόν","G5547"]],"4":[["εἰ","G1487"],["μὲν","G3303"],["γὰρ","G1063"],["ὁ","G3588"],["ἐρχόμενος","G2064"],["ἄλλον","G243"],["Ἰησοῦν","G2424"],["κηρύσσει","G2784"],["ὃν","G3739"],["οὐκ","G3756"],["ἐκηρύξαμεν","G2784"],["ἢ","G2228"],["πνεῦμα","G4151"],["ἕτερον","G2087"],["λαμβάνετε","G2983"],["ὃ","G3739"],["οὐκ","G3756"],["ἐλάβετε","G2983"],["ἢ","G2228"],["εὐαγγέλιον","G2098"],["ἕτερον","G2087"],["ὃ","G3739"],["οὐκ","G3756"],["ἐδέξασθε","G1209"],["καλῶς","G2573"],["ἀνέχεσθε","G430"]],"5":[["Λογίζομαι","G3049"],["γὰρ","G1063"],["μηδὲν","G3367"],["ὑστερηκέναι","G5302"],["τῶν","G3588"],["Ὑπερλίαν","G5228"],["ἀποστόλων","G652"]],"6":[["εἰ","G1487"],["δὲ","G1161"],["καὶ","G2532"],["ἰδιώτης","G2399"],["τῷ","G3588"],["λόγῳ","G3056"],["ἀλλ’","G235"],["οὐ","G3756"],["τῇ","G3588"],["γνώσει","G1108"],["ἀλλ’","G235"],["ἐν","G1722"],["παντὶ","G3956"],["φανερώσαντες","G5319"],["ἐν","G1722"],["πᾶσιν","G3956"],["εἰς","G1519"],["ὑμᾶς","G4771"]],"7":[["Ἢ","G2228"],["ἁμαρτίαν","G266"],["ἐποίησα","G4160"],["ἐμαυτὸν","G1683"],["ταπεινῶν","G5013"],["ἵνα","G2443"],["ὑμεῖς","G4771"],["ὑψωθῆτε","G5312"],["ὅτι","G3754"],["δωρεὰν","G1432"],["τὸ","G3588"],["τοῦ","G3588"],["Θεοῦ","G2316"],["εὐαγγέλιον","G2098"],["εὐηγγελισάμην","G2097"],["ὑμῖν","G4771"]],"8":[["ἄλλας","G243"],["ἐκκλησίας","G1577"],["ἐσύλησα","G4813"],["λαβὼν","G2983"],["ὀψώνιον","G3800"],["πρὸς","G4314"],["τὴν","G3588"],["ὑμῶν","G4771"],["διακονίαν","G1248"]],"9":[["καὶ","G2532"],["παρὼν","G3918"],["πρὸς","G4314"],["ὑμᾶς","G4771"],["καὶ","G2532"],["ὑστερηθεὶς","G5302"],["οὐ","G3756"],["κατενάρκησα","G2655"],["οὐθενός","G3762"],["τὸ","G3588"],["γὰρ","G1063"],["ὑστέρημά","G5303"],["μου","G1473"],["προσανεπλήρωσαν","G4322"],["οἱ","G3588"],["ἀδελφοὶ","G80"],["ἐλθόντες","G2064"],["ἀπὸ","G575"],["Μακεδονίας","G3109"],["καὶ","G2532"],["ἐν","G1722"],["παντὶ","G3956"],["ἀβαρῆ","G4"],["ἐμαυτὸν","G1683"],["ὑμῖν","G4771"],["ἐτήρησα","G5083"],["καὶ","G2532"],["τηρήσω","G5083"]],"10":[["ἔστιν","G1510"],["ἀλήθεια","G225"],["Χριστοῦ","G5547"],["ἐν","G1722"],["ἐμοὶ","G1473"],["ὅτι","G3754"],["ἡ","G3588"],["καύχησις","G2746"],["αὕτη","G3778"],["οὐ","G3756"],["φραγήσεται","G5420"],["εἰς","G1519"],["ἐμὲ","G1473"],["ἐν","G1722"],["τοῖς","G3588"],["κλίμασιν","G2824"],["τῆς","G3588"],["Ἀχαΐας","G882"]],"11":[["διὰ","G1223"],["τί","G5101"],["ὅτι","G3754"],["οὐκ","G3756"],["ἀγαπῶ","G25"],["ὑμᾶς","G4771"],["ὁ","G3588"],["Θεὸς","G2316"],["οἶδεν","G1492"]],"12":[["Ὃ","G3739"],["δὲ","G1161"],["ποιῶ","G4160"],["καὶ","G2532"],["ποιήσω","G4160"],["ἵνα","G2443"],["ἐκκόψω","G1581"],["τὴν","G3588"],["ἀφορμὴν","G874"],["τῶν","G3588"],["θελόντων","G2309"],["ἀφορμήν","G874"],["ἵνα","G2443"],["ἐν","G1722"],["ᾧ","G3739"],["καυχῶνται","G2744"],["εὑρεθῶσιν","G2147"],["καθὼς","G2531"],["καὶ","G2532"],["ἡμεῖς","G1473"]],"13":[["οἱ","G3588"],["γὰρ","G1063"],["τοιοῦτοι","G5108"],["ψευδαπόστολοι","G5570"],["ἐργάται","G2040"],["δόλιοι","G1386"],["μετασχηματιζόμενοι","G3345"],["εἰς","G1519"],["ἀποστόλους","G652"],["Χριστοῦ","G5547"]],"14":[["καὶ","G2532"],["οὐ","G3756"],["θαῦμα","G2295"],["αὐτὸς","G846"],["γὰρ","G1063"],["ὁ","G3588"],["Σατανᾶς","G4567"],["μετασχηματίζεται","G3345"],["εἰς","G1519"],["ἄγγελον","G32"],["φωτός","G5457"]],"15":[["οὐ","G3756"],["μέγα","G3173"],["οὖν","G3767"],["εἰ","G1487"],["καὶ","G2532"],["οἱ","G3588"],["διάκονοι","G1249"],["αὐτοῦ","G846"],["μετασχηματίζονται","G3345"],["ὡς","G5613"],["διάκονοι","G1249"],["δικαιοσύνης","G1343"],["ὧν","G3739"],["τὸ","G3588"],["τέλος","G5056"],["ἔσται","G1510"],["κατὰ","G2596"],["τὰ","G3588"],["ἔργα","G2041"],["αὐτῶν","G846"]],"16":[["Πάλιν","G3825"],["λέγω","G3004"],["μή","G3361"],["τίς","G5100"],["με","G1473"],["δόξῃ","G1380"],["ἄφρονα","G878"],["εἶναι","G1510"],["εἰ","G1487"],["δὲ","G1161"],["μή¦γε","G1490"],["κἂν","G2579"],["ὡς","G5613"],["ἄφρονα","G878"],["δέξασθέ","G1209"],["με","G1473"],["ἵνα","G2443"],["κἀγὼ","G2504"],["μικρόν","G3398"],["τι","G5100"],["καυχήσωμαι","G2744"]],"17":[["ὃ","G3739"],["λαλῶ","G2980"],["οὐ","G3756"],["κατὰ","G2596"],["Κύριον","G2962"],["λαλῶ","G2980"],["ἀλλ’","G235"],["ὡς","G5613"],["ἐν","G1722"],["ἀφροσύνῃ","G877"],["ἐν","G1722"],["ταύτῃ","G3778"],["τῇ","G3588"],["ὑποστάσει","G5287"],["τῆς","G3588"],["καυχήσεως","G2746"]],"18":[["ἐπεὶ","G1893"],["πολλοὶ","G4183"],["καυχῶνται","G2744"],["κατὰ","G2596"],["τὴν","G3588"],["σάρκα","G4561"],["κἀγὼ","G2504"],["καυχήσομαι","G2744"]],"19":[["ἡδέως","G2234"],["γὰρ","G1063"],["ἀνέχεσθε","G430"],["τῶν","G3588"],["ἀφρόνων","G878"],["φρόνιμοι","G5429"],["ὄντες","G1510"]],"20":[["ἀνέχεσθε","G430"],["γὰρ","G1063"],["εἴ","G1487"],["τις","G5100"],["ὑμᾶς","G4771"],["καταδουλοῖ","G2615"],["εἴ","G1487"],["τις","G5100"],["κατεσθίει","G2719"],["εἴ","G1487"],["τις","G5100"],["λαμβάνει","G2983"],["εἴ","G1487"],["τις","G5100"],["ἐπαίρεται","G1869"],["εἴ","G1487"],["τις","G5100"],["εἰς","G1519"],["πρόσωπον","G4383"],["ὑμᾶς","G4771"],["δέρει","G1194"]],"21":[["κατὰ","G2596"],["ἀτιμίαν","G819"],["λέγω","G3004"],["ὡς","G5613"],["ὅτι","G3754"],["ἡμεῖς","G1473"],["ἠσθενήκαμεν","G770"],["Ἐν","G1722"],["ᾧ","G3739"],["δ’","G1161"],["ἄν","G302"],["τις","G5100"],["τολμᾷ","G5111"],["ἐν","G1722"],["ἀφροσύνῃ","G877"],["λέγω","G3004"],["τολμῶ","G5111"],["κἀγώ","G2504"]],"22":[["Ἑβραῖοί","G1445"],["εἰσιν","G1510"],["κἀγώ","G2504"],["Ἰσραηλῖταί","G2475"],["εἰσιν","G1510"],["κἀγώ","G2504"],["σπέρμα","G4690"],["Ἀβραάμ","G11"],["εἰσιν","G1510"],["κἀγώ","G2504"]],"23":[["διάκονοι","G1249"],["Χριστοῦ","G5547"],["εἰσιν","G1510"],["παραφρονῶν","G3912"],["λαλῶ","G2980"],["ὑπὲρ","G5228"],["ἐγώ","G1473"],["ἐν","G1722"],["κόποις","G2873"],["περισσοτέρως","G4057"],["ἐν","G1722"],["φυλακαῖς","G5438"],["περισσοτέρως","G4057"],["ἐν","G1722"],["πληγαῖς","G4127"],["ὑπερβαλλόντως","G5234"],["ἐν","G1722"],["θανάτοις","G2288"],["πολλάκις","G4178"]],"24":[["Ὑπὸ","G5259"],["Ἰουδαίων","G2453"],["πεντάκις","G3999"],["τεσσεράκοντα","G5062"],["παρὰ","G3844"],["μίαν","G1520"],["ἔλαβον","G2983"]],"25":[["τρὶς","G5151"],["ἐραβδίσθην","G4463"],["ἅπαξ","G530"],["ἐλιθάσθην","G3034"],["τρὶς","G5151"],["ἐναυάγησα","G3489"],["νυχθήμερον","G3574"],["ἐν","G1722"],["τῷ","G3588"],["βυθῷ","G1037"],["πεποίηκα","G4160"]],"26":[["ὁδοιπορίαις","G3597"],["πολλάκις","G4178"],["κινδύνοις","G2794"],["ποταμῶν","G4215"],["κινδύνοις","G2794"],["λῃστῶν","G3027"],["κινδύνοις","G2794"],["ἐκ","G1537"],["γένους","G1085"],["κινδύνοις","G2794"],["ἐξ","G1537"],["ἐθνῶν","G1484"],["κινδύνοις","G2794"],["ἐν","G1722"],["πόλει","G4172"],["κινδύνοις","G2794"],["ἐν","G1722"],["ἐρημίᾳ","G2047"],["κινδύνοις","G2794"],["ἐν","G1722"],["θαλάσσῃ","G2281"],["κινδύνοις","G2794"],["ἐν","G1722"],["ψευδαδέλφοις","G5569"]],"27":[["κόπῳ","G2873"],["καὶ","G2532"],["μόχθῳ","G3449"],["ἐν","G1722"],["ἀγρυπνίαις","G70"],["πολλάκις","G4178"],["ἐν","G1722"],["λιμῷ","G3042"],["καὶ","G2532"],["δίψει","G1373"],["ἐν","G1722"],["νηστείαις","G3521"],["πολλάκις","G4178"],["ἐν","G1722"],["ψύχει","G5592"],["καὶ","G2532"],["γυμνότητι","G1132"]],"28":[["Χωρὶς","G5565"],["τῶν","G3588"],["παρεκτὸς","G3924"],["ἡ","G3588"],["ἐπίστασίς","G1999"],["μοι","G1473"],["ἡ","G3588"],["καθ’","G2596"],["ἡμέραν","G2250"],["ἡ","G3588"],["μέριμνα","G3308"],["πασῶν","G3956"],["τῶν","G3588"],["ἐκκλησιῶν","G1577"]],"29":[["τίς","G5101"],["ἀσθενεῖ","G770"],["καὶ","G2532"],["οὐκ","G3756"],["ἀσθενῶ","G770"],["τίς","G5101"],["σκανδαλίζεται","G4624"],["καὶ","G2532"],["οὐκ","G3756"],["ἐγὼ","G1473"],["πυροῦμαι","G4448"]],"30":[["Εἰ","G1487"],["καυχᾶσθαι","G2744"],["δεῖ","G1163"],["τὰ","G3588"],["τῆς","G3588"],["ἀσθενείας","G769"],["μου","G1473"],["καυχήσομαι","G2744"]],"31":[["ὁ","G3588"],["Θεὸς","G2316"],["καὶ","G2532"],["Πατὴρ","G3962"],["τοῦ","G3588"],["Κυρίου","G2962"],["Ἰησοῦ","G2424"],["οἶδεν","G1492"],["ὁ","G3588"],["ὢν","G1510"],["εὐλογητὸς","G2128"],["εἰς","G1519"],["τοὺς","G3588"],["αἰῶνας","G165"],["ὅτι","G3754"],["οὐ","G3756"],["ψεύδομαι","G5574"]],"32":[["ἐν","G1722"],["Δαμασκῷ","G1154"],["ὁ","G3588"],["ἐθνάρχης","G1481"],["Ἁρέτα","G702"],["τοῦ","G3588"],["βασιλέως","G935"],["ἐφρούρει","G5432"],["τὴν","G3588"],["πόλιν","G4172"],["Δαμασκηνῶν","G1153"],["πιάσαι","G4084"],["με","G1473"]],"33":[["καὶ","G2532"],["διὰ","G1223"],["θυρίδος","G2376"],["ἐν","G1722"],["σαργάνῃ","G4553"],["ἐχαλάσθην","G5465"],["διὰ","G1223"],["τοῦ","G3588"],["τείχους","G5038"],["καὶ","G2532"],["ἐξέφυγον","G1628"],["τὰς","G3588"],["χεῖρας","G5495"],["αὐτοῦ","G846"]]}}